qwen_mt_tool/__init__.py
qwen_mt_tool/cli.py
qwen_mt_tool/config.py
qwen_mt_tool/key_pool.py
qwen_mt_tool/logging_setup.py
qwen_mt_tool/translator.py
qwen_mt_tool/utils.py
qwen_mt_tool-0.2.0.dist-info/METADATA
qwen_mt_tool-0.2.0.dist-info/WHEEL
qwen_mt_tool-0.2.0.dist-info/entry_points.txt
qwen_mt_tool-0.2.0.dist-info/RECORD
