Metadata-Version: 2.4
Name: qwen-mt-tool
Version: 0.2.0
Summary: A CLI tool for translating markdown files using Qwen-MT
Project-URL: Homepage, https://github.com/yourusername/qwen-mt-tool
Project-URL: Repository, https://github.com/yourusername/qwen-mt-tool
Author-email: Your Name <your.email@example.com>
License-Expression: MIT
Classifier: License :: OSI Approved :: MIT License
Classifier: Operating System :: OS Independent
Classifier: Programming Language :: Python :: 3
Requires-Python: >=3.10
Requires-Dist: colorlog>=6.0.0
Requires-Dist: openai>=1.0.0
